linkedin_jobs_api/__init__.py
linkedin_jobs_api/client.py
linkedin_jobs_api/parser.py
linkedin_jobs_api/url_builder.py
linkedin_jobs_api_py-0.1.3.dist-info/licenses/LICENSE
linkedin_jobs_api_py-0.1.3.dist-info/METADATA
linkedin_jobs_api_py-0.1.3.dist-info/WHEEL
linkedin_jobs_api_py-0.1.3.dist-info/top_level.txt
linkedin_jobs_api_py-0.1.3.dist-info/RECORD
