Metadata-Version: 2.4
Name: linkedin-jobs-api-py
Version: 0.1.3
Summary: Unofficial LinkedIn Jobs scraper API for Python
Author-email: Anselme Wilfried R OUEDRAOGO <wilfried.ouedraogo@itpartages.com>
License: MIT License
Project-URL: Homepage, https://github.com/ANSELME-TIC/linkedin-jobs-api-py
Project-URL: Documentation, https://github.com/ANSELME-TIC/linkedin-jobs-api-py#readme
Project-URL: Repository, https://github.com/ANSELME-TIC/linkedin-jobs-api-py
Project-URL: Issues, https://github.com/ANSELME-TIC/linkedin-jobs-api-py/issues
Requires-Python: >=3.9
License-File: LICENSE
Requires-Dist: requests>=2.32.0
Requires-Dist: selectolax>=0.4.3
Provides-Extra: dev
Requires-Dist: pytest>=8.4.2; extra == "dev"
Requires-Dist: pytest-cov; extra == "dev"
Requires-Dist: requests-mock; extra == "dev"
Requires-Dist: black; extra == "dev"
Requires-Dist: ruff; extra == "dev"
Requires-Dist: mypy; extra == "dev"
Dynamic: license-file
